llama_index/postprocessor/ibm/__init__.py
llama_index/postprocessor/ibm/base.py
llama_index/postprocessor/ibm/utils.py
llama_index_postprocessor_ibm-0.3.1.dist-info/METADATA
llama_index_postprocessor_ibm-0.3.1.dist-info/WHEEL
llama_index_postprocessor_ibm-0.3.1.dist-info/RECORD
