Metadata-Version: 2.4
Name: llama-index-postprocessor-ibm
Version: 0.3.1
Summary: llama-index postprocessor IBM watsonx.ai integration
Author: IBM
License-Expression: MIT
Requires-Python: <3.13,>=3.10
Requires-Dist: ibm-watsonx-ai>=1.3.36
Requires-Dist: llama-index-core<0.15,>=0.13.0
Requires-Dist: pyarrow
